{
  "students": [
    {
      "id": 1,
      "personal_data": {
        "roll": "448903",
        "registration": "748596321012",
        "student_name": "Naimul Islam",
        "father_name": "Abdul Halim",
        "mother_name": "Salma Akter",
        "date_of_birth": "2002-05-15",
        "gender": "male",
        "session": "2020-2021",
        "name_of_industry": "Dhaka Polytechnic Institute",
        "department": "Computer Science and Technology"
      },
      "subject_info": {}
    },
    {
      "id": 2,
      "personal_data": {
        "roll": "123456",
        "registration": "987654321098",
        "student_name": "Fariha Akter",
        "father_name": "Jamal Hossain",
        "mother_name": "Tahmina Begum",
        "date_of_birth": "2004-11-21",
        "gender": "female",
        "session": "2022-2023",
        "name_of_industry": "Mymensingh Polytechnic Institute",
        "department": "Electronics Technology"
      },
      "subject_info": {}
    },
    {
      "id": 3,
      "personal_data": {
        "roll": "789012",
        "registration": "112233445566",
        "student_name": "Rafiq Uddin",
        "father_name": "Kamal Uddin",
        "mother_name": "Shirin Akter",
        "date_of_birth": "2001-08-03",
        "gender": "male",
        "session": "2018-2019",
        "name_of_industry": "Rajshahi Polytechnic Institute",
        "department": "Civil Technology"
      },
      "subject_info": {}
    },
    {
      "id": 4,
      "personal_data": {
        "roll": "345678",
        "registration": "665544332211",
        "student_name": "Sumaiya Khanom",
        "father_name": "Zahid Hasan",
        "mother_name": "Fatema Begum",
        "date_of_birth": "2003-02-28",
        "gender": "female",
        "session": "2022-2023",
        "name_of_industry": "Bogura Polytechnic Institute",
        "department": "Electrical Technology"
      },
      "subject_info": {}
    },
    {
      "id": 5,
      "personal_data": {
        "roll": "901234",
        "registration": "889900112233",
        "student_name": "Mehedi Hasan",
        "father_name": "Sajjad Hossain",
        "mother_name": "Jahanara Begum",
        "date_of_birth": "2000-09-10",
        "gender": "male",
        "session": "2018-2019",
        "name_of_industry": "Khulna Polytechnic Institute",
        "department": "Mechanical Technology"
      },
      "subject_info": {}
    },
    {
      "id": 6,
      "personal_data": {
        "roll": "567890",
        "registration": "445566778899",
        "student_name": "Sadia Islam",
        "father_name": "Ruhul Amin",
        "mother_name": "Farida Yasmin",
        "date_of_birth": "2005-07-07",
        "gender": "female",
        "session": "2024-2025",
        "name_of_industry": "Sylhet Polytechnic Institute",
        "department": "Accounting"
      },
      "subject_info": {}
    },
    {
      "id": 7,
      "personal_data": {
        "roll": "112233",
        "registration": "998877665544",
        "student_name": "Asif Ahmed",
        "father_name": "Masud Rana",
        "mother_name": "Monira Begum",
        "date_of_birth": "2001-03-19",
        "gender": "male",
        "session": "2018-2019",
        "name_of_industry": "Chattogram Polytechnic Institute",
        "department": "Power Technology"
      },
      "subject_info": {}
    },
    {
      "id": 8,
      "personal_data": {
        "roll": "445566",
        "registration": "332211009988",
        "student_name": "Nusrat Jahan",
        "father_name": "Anwar Hossain",
        "mother_name": "Shamima Akter",
        "date_of_birth": "2004-12-05",
        "gender": "female",
        "session": "2022-2023",
        "name_of_industry": "Pabna Polytechnic Institute",
        "department": "Electro-Medical Technology"
      },
      "subject_info": {}
    },
    {
      "id": 9,
      "personal_data": {
        "roll": "778899",
        "registration": "556677889900",
        "student_name": "Rashed Khan",
        "father_name": "Ali Ashraf",
        "mother_name": "Sultana Begum",
        "date_of_birth": "2002-06-25",
        "gender": "male",
        "session": "2020-2021",
        "name_of_industry": "Rangpur Polytechnic Institute",
        "department": "Civil Technology"
      },
      "subject_info": {}
    },
    {
      "id": 10,
      "personal_data": {
        "roll": "001122",
        "registration": "223344556677",
        "student_name": "Sabina Yasmin",
        "father_name": "Motiur Rahman",
        "mother_name": "Momtaz Begum",
        "date_of_birth": "2005-10-14",
        "gender": "female",
        "session": "2024-2025",
        "name_of_industry": "Barishal Polytechnic Institute",
        "department": "Marketing"
      },
      "subject_info": {}
    },
    {
      "id": 11,
      "personal_data": {
        "roll": "334455",
        "registration": "887766554433",
        "student_name": "Tareq Aziz",
        "father_name": "Golam Kibria",
        "mother_name": "Hasina Akter",
        "date_of_birth": "2003-01-09",
        "gender": "male",
        "session": "2020-2021",
        "name_of_industry": "Feni Polytechnic Institute",
        "department": "Electrical Technology"
      },
      "subject_info": {}
    },
    {
      "id": 12,
      "personal_data": {
        "roll": "667788",
        "registration": "990011223344",
        "student_name": "Marufa Akter",
        "father_name": "Iqbal Hossain",
        "mother_name": "Shahnaz Begum",
        "date_of_birth": "2004-03-22",
        "gender": "female",
        "session": "2022-2023",
        "name_of_industry": "Brahmanbaria Polytechnic Institute",
        "department": "Electronics Technology"
      },
      "subject_info": {}
    },
    {
      "id": 13,
      "personal_data": {
        "roll": "990011",
        "registration": "112233445566",
        "student_name": "Sabbir Ahmed",
        "father_name": "Abul Kashem",
        "mother_name": "Parul Akter",
        "date_of_birth": "2001-07-30",
        "gender": "male",
        "session": "2018-2019",
        "name_of_industry": "Cumilla Polytechnic Institute",
        "department": "Computer Science and Technology"
      },
      "subject_info": {}
    },
    {
      "id": 14,
      "personal_data": {
        "roll": "223344",
        "registration": "778899001122",
        "student_name": "Jannatul Ferdous",
        "father_name": "Harun Or Rashid",
        "mother_name": "Hazera Khatun",
        "date_of_birth": "2003-12-11",
        "gender": "female",
        "session": "2022-2023",
        "name_of_industry": "Gazipur Polytechnic Institute",
        "department": "Business Management"
      },
      "subject_info": {}
    },
    {
      "id": 15,
      "personal_data": {
        "roll": "556677",
        "registration": "334455667788",
        "student_name": "Mahmudul Hasan",
        "father_name": "Monir Hossain",
        "mother_name": "Nasima Begum",
        "date_of_birth": "2000-04-01",
        "gender": "male",
        "session": "2018-2019",
        "name_of_industry": "Jessore Polytechnic Institute",
        "department": "Agronomy"
      },
      "subject_info": {}
    },
    {
      "id": 16,
      "personal_data": {
        "roll": "889900",
        "registration": "998877665544",
        "student_name": "Tanzina Akter",
        "father_name": "Abdul Latif",
        "mother_name": "Rahela Begum",
        "date_of_birth": "2005-09-29",
        "gender": "female",
        "session": "2024-2025",
        "name_of_industry": "Kushtia Polytechnic Institute",
        "department": "Yarn Manufacturing"
      },
      "subject_info": {}
    },
    {
      "id": 17,
      "personal_data": {
        "roll": "112233",
        "registration": "223344556677",
        "student_name": "Alomgir Hossain",
        "father_name": "Habibur Rahman",
        "mother_name": "Ayesha Khatun",
        "date_of_birth": "2001-01-16",
        "gender": "male",
        "session": "2018-2019",
        "name_of_industry": "Madaripur Polytechnic Institute",
        "department": "Horticulture"
      },
      "subject_info": {}
    },
    {
      "id": 18,
      "personal_data": {
        "roll": "445566",
        "registration": "889900112233",
        "student_name": "Sharmin Akter",
        "father_name": "Amirul Islam",
        "mother_name": "Roksana Begum",
        "date_of_birth": "2004-06-08",
        "gender": "female",
        "session": "2022-2023",
        "name_of_industry": "Moulvibazar Polytechnic Institute",
        "department": "Livestock Management"
      },
      "subject_info": {}
    },
    {
      "id": 19,
      "personal_data": {
        "roll": "778899",
        "registration": "556677889900",
        "student_name": "Mamunur Rashid",
        "father_name": "Shahidul Islam",
        "mother_name": "Kohinoor Begum",
        "date_of_birth": "2002-08-12",
        "gender": "male",
        "session": "2020-2021",
        "name_of_industry": "Narayanganj Polytechnic Institute",
        "department": "Fisheries"
      },
      "subject_info": {}
    },
    {
      "id": 20,
      "personal_data": {
        "roll": "001122",
        "registration": "445566778899",
        "student_name": "Rima Akhter",
        "father_name": "Abul Kalam",
        "mother_name": "Shila Begum",
        "date_of_birth": "2005-02-18",
        "gender": "female",
        "session": "2024-2025",
        "name_of_industry": "Dinajpur Polytechnic Institute",
        "department": "Yarn Manufacturing"
      },
      "subject_info": {}
    },
    {
      "id": 21,
      "personal_data": {
        "roll": "334455",
        "registration": "990011223344",
        "student_name": "Saimon Rahman",
        "father_name": "Ziaul Haque",
        "mother_name": "Sumiya Akter",
        "date_of_birth": "2003-05-27",
        "gender": "male",
        "session": "2020-2021",
        "name_of_industry": "Gopalganj Polytechnic Institute",
        "department": "Wet Processing Technology"
      },
      "subject_info": {}
    },
    {
      "id": 22,
      "personal_data": {
        "roll": "667788",
        "registration": "778899001122",
        "student_name": "Sanjida Islam",
        "father_name": "Rafiqul Islam",
        "mother_name": "Nilufa Yasmin",
        "date_of_birth": "2004-09-03",
        "gender": "female",
        "session": "2022-2023",
        "name_of_industry": "Sirajganj Polytechnic Institute",
        "department": "Apparel Manufacturing"
      },
      "subject_info": {}
    },
    {
      "id": 23,
      "personal_data": {
        "roll": "990011",
        "registration": "334455667788",
        "student_name": "Rifat Ahmed",
        "father_name": "Yousuf Ali",
        "mother_name": "Hosneara Begum",
        "date_of_birth": "2001-10-10",
        "gender": "male",
        "session": "2018-2019",
        "name_of_industry": "Thakurgaon Polytechnic Institute",
        "department": "Civil Technology"
      },
      "subject_info": {}
    },
    {
      "id": 24,
      "personal_data": {
        "roll": "223344",
        "registration": "998877665544",
        "student_name": "Bristy Akter",
        "father_name": "Abdul Majid",
        "mother_name": "Firoza Begum",
        "date_of_birth": "2003-04-20",
        "gender": "female",
        "session": "2022-2023",
        "name_of_industry": "Pirojpur Polytechnic Institute",
        "department": "Electrical Technology"
      },
      "subject_info": {}
    },
    {
      "id": 25,
      "personal_data": {
        "roll": "556677",
        "registration": "223344556677",
        "student_name": "Emon Hossain",
        "father_name": "Ashraful Islam",
        "mother_name": "Morzina Khatun",
        "date_of_birth": "2000-12-04",
        "gender": "male",
        "session": "2018-2019",
        "name_of_industry": "Patuakhali Polytechnic Institute",
        "department": "Computer Science and Technology"
      },
      "subject_info": {}
    },
    {
      "id": 26,
      "personal_data": {
        "roll": "889900",
        "registration": "889900112233",
        "student_name": "Taslima Begum",
        "father_name": "Kamruzzaman",
        "mother_name": "Rabeya Begum",
        "date_of_birth": "2005-06-15",
        "gender": "female",
        "session": "2024-2025",
        "name_of_industry": "Mymensingh Mohila Polytechnic Institute",
        "department": "Finance"
      },
      "subject_info": {}
    },
    {
      "id": 27,
      "personal_data": {
        "roll": "112233",
        "registration": "556677889900",
        "student_name": "Md. Shahin",
        "father_name": "Abdul Aziz",
        "mother_name": "Hosna Begum",
        "date_of_birth": "2001-08-28",
        "gender": "male",
        "session": "2018-2019",
        "name_of_industry": "Khagrachari Polytechnic Institute",
        "department": "Mechanical Technology"
      },
      "subject_info": {}
    },
    {
      "id": 28,
      "personal_data": {
        "roll": "445566",
        "registration": "445566778899",
        "student_name": "Mitu Akter",
        "father_name": "Badrul Islam",
        "mother_name": "Mina Akter",
        "date_of_birth": "2004-01-05",
        "gender": "female",
        "session": "2022-2023",
        "name_of_industry": "Cox's Bazar Polytechnic Institute",
        "department": "Horticulture"
      },
      "subject_info": {}
    },
    {
      "id": 29,
      "personal_data": {
        "roll": "778899",
        "registration": "112233445566",
        "student_name": "Faridul Islam",
        "father_name": "Shafiqul Islam",
        "mother_name": "Shahnaj Parvin",
        "date_of_birth": "2002-09-17",
        "gender": "male",
        "session": "2020-2021",
        "name_of_industry": "Satkhira Polytechnic Institute",
        "department": "Livestock Management"
      },
      "subject_info": {}
    },
    {
      "id": 30,
      "personal_data": {
        "roll": "001122",
        "registration": "778899001122",
        "student_name": "Laboni Akter",
        "father_name": "Anisur Rahman",
        "mother_name": "Sumona Begum",
        "date_of_birth": "2005-11-20",
        "gender": "female",
        "session": "2024-2025",
        "name_of_industry": "Tangail Polytechnic Institute",
        "department": "Fisheries"
      },
      "subject_info": {}
    },
    {
      "id": 31,
      "personal_data": {
        "roll": "334455",
        "registration": "334455667788",
        "student_name": "Samiul Alam",
        "father_name": "Babul Hossain",
        "mother_name": "Shila Akter",
        "date_of_birth": "2003-07-02",
        "gender": "male",
        "session": "2020-2021",
        "name_of_industry": "Natore Polytechnic Institute",
        "department": "Agronomy"
      },
      "subject_info": {}
    },
    {
      "id": 32,
      "personal_data": {
        "roll": "667788",
        "registration": "998877665544",
        "student_name": "Jahanara Begum",
        "father_name": "Aminul Haque",
        "mother_name": "Farjana Begum",
        "date_of_birth": "2004-08-16",
        "gender": "female",
        "session": "2022-2023",
        "name_of_industry": "Bogura Mohila Polytechnic Institute",
        "department": "Accounting"
      },
      "subject_info": {}
    },
    {
      "id": 33,
      "personal_data": {
        "roll": "990011",
        "registration": "223344556677",
        "student_name": "Shohel Rana",
        "father_name": "Habibullah",
        "mother_name": "Rokeya Khatun",
        "date_of_birth": "2001-02-24",
        "gender": "male",
        "session": "2018-2019",
        "name_of_industry": "Noakhali Polytechnic Institute",
        "department": "Power Technology"
      },
      "subject_info": {}
    },
    {
      "id": 34,
      "personal_data": {
        "roll": "223344",
        "registration": "889900112233",
        "student_name": "Khairun Nahar",
        "father_name": "Rezaul Karim",
        "mother_name": "Asma Akter",
        "date_of_birth": "2003-09-08",
        "gender": "female",
        "session": "2022-2023",
        "name_of_industry": "Lalmonirhat Polytechnic Institute",
        "department": "Wet Processing Technology"
      },
      "subject_info": {}
    },
    {
      "id": 35,
      "personal_data": {
        "roll": "556677",
        "registration": "556677889900",
        "student_name": "Kamrul Hasan",
        "father_name": "Akramul Haque",
        "mother_name": "Shajahan Begum",
        "date_of_birth": "2000-11-29",
        "gender": "male",
        "session": "2018-2019",
        "name_of_industry": "Joypurhat Polytechnic Institute",
        "department": "Fabric Manufacturing"
      },
      "subject_info": {}
    },
    {
      "id": 36,
      "personal_data": {
        "roll": "889900",
        "registration": "445566778899",
        "student_name": "Sultana Parvin",
        "father_name": "Shahidul Alam",
        "mother_name": "Ranu Akter",
        "date_of_birth": "2005-08-01",
        "gender": "female",
        "session": "2024-2025",
        "name_of_industry": "Gaibandha Polytechnic Institute",
        "department": "Business Management"
      },
      "subject_info": {}
    },
    {
      "id": 37,
      "personal_data": {
        "roll": "112233",
        "registration": "990011223344",
        "student_name": "Tariqul Islam",
        "father_name": "Monirul Islam",
        "mother_name": "Kamrun Nahar",
        "date_of_birth": "2001-04-14",
        "gender": "male",
        "session": "2018-2019",
        "name_of_industry": "Netrokona Polytechnic Institute",
        "department": "Apparel Manufacturing"
      },
      "subject_info": {}
    },
    {
      "id": 38,
      "personal_data": {
        "roll": "445566",
        "registration": "778899001122",
        "student_name": "Nadia Tasnim",
        "father_name": "Siddiqur Rahman",
        "mother_name": "Momena Begum",
        "date_of_birth": "2004-10-23",
        "gender": "female",
        "session": "2022-2023",
        "name_of_industry": "Bandarban Polytechnic Institute",
        "department": "Finance"
      },
      "subject_info": {}
    },
    {
      "id": 39,
      "personal_data": {
        "roll": "778899",
        "registration": "334455667788",
        "student_name": "Rakib Hossain",
        "father_name": "Sirajul Islam",
        "mother_name": "Nurjahan Begum",
        "date_of_birth": "2002-03-05",
        "gender": "male",
        "session": "2020-2021",
        "name_of_industry": "Rangamati Polytechnic Institute",
        "department": "Yarn Manufacturing"
      },
      "subject_info": {}
    },
    {
      "id": 40,
      "personal_data": {
        "roll": "001122",
        "registration": "998877665544",
        "student_name": "Afrin Akter",
        "father_name": "Abdullah Al Mahmud",
        "mother_name": "Khaleda Begum",
        "date_of_birth": "2005-01-19",
        "gender": "female",
        "session": "2024-2025",
        "name_of_industry": "Bogra Government Polytechnic Institute",
        "department": "Accounting"
      },
      "subject_info": {}
    },
    {
      "id": 41,
      "personal_data": {
        "roll": "334455",
        "registration": "223344556677",
        "student_name": "Md. Faisal",
        "father_name": "Fazlul Haque",
        "mother_name": "Selina Begum",
        "date_of_birth": "2003-11-25",
        "gender": "male",
        "session": "2022-2023",
        "name_of_industry": "Dhaka Girls Polytechnic Institute",
        "department": "Electronics Technology"
      },
      "subject_info": {}
    },
    {
      "id": 42,
      "personal_data": {
        "roll": "667788",
        "registration": "889900112233",
        "student_name": "Sumiya Khatun",
        "father_name": "Abdur Razzaq",
        "mother_name": "Shapla Begum",
        "date_of_birth": "2004-05-13",
        "gender": "female",
        "session": "2022-2023",
        "name_of_industry": "Rajshahi Mohila Polytechnic Institute",
        "department": "Marketing"
      },
      "subject_info": {}
    },
    {
      "id": 43,
      "personal_data": {
        "roll": "990011",
        "registration": "556677889900",
        "student_name": "Sajeeb Talukdar",
        "father_name": "Amzad Hossain",
        "mother_name": "Sumi Akter",
        "date_of_birth": "2001-06-28",
        "gender": "male",
        "session": "2018-2019",
        "name_of_industry": "Sylhet Mohila Polytechnic Institute",
        "department": "Civil Technology"
      },
      "subject_info": {}
    },
    {
      "id": 44,
      "personal_data": {
        "roll": "223344",
        "registration": "445566778899",
        "student_name": "Liza Akter",
        "father_name": "Moniruzzaman",
        "mother_name": "Anjuman Ara Begum",
        "date_of_birth": "2003-02-07",
        "gender": "female",
        "session": "2022-2023",
        "name_of_industry": "Barishal Mohila Polytechnic Institute",
        "department": "Wet Processing Technology"
      },
      "subject_info": {}
    },
    {
      "id": 45,
      "personal_data": {
        "roll": "556677",
        "registration": "990011223344",
        "student_name": "Saddam Hossain",
        "father_name": "Jamir Uddin",
        "mother_name": "Kohinoor Begum",
        "date_of_birth": "2000-09-19",
        "gender": "male",
        "session": "2018-2019",
        "name_of_industry": "Jashore Polytechnic Institute",
        "department": "Computer Science and Technology"
      },
      "subject_info": {}
    },
    {
      "id": 46,
      "personal_data": {
        "roll": "889900",
        "registration": "778899001122",
        "student_name": "Israt Jahan",
        "father_name": "Faruk Hossain",
        "mother_name": "Salma Begum",
        "date_of_birth": "2005-04-04",
        "gender": "female",
        "session": "2024-2025",
        "name_of_industry": "Pabna Mohila Polytechnic Institute",
        "department": "Apparel Manufacturing"
      },
      "subject_info": {}
    },
    {
      "id": 47,
      "personal_data": {
        "roll": "112233",
        "registration": "334455667788",
        "student_name": "Arif Islam",
        "father_name": "Abdul Hai",
        "mother_name": "Shahanara Akter",
        "date_of_birth": "2001-05-18",
        "gender": "male",
        "session": "2018-2019",
        "name_of_industry": "Mymensingh Engineering College",
        "department": "Mechanical Technology"
      },
      "subject_info": {}
    },
    {
      "id": 48,
      "personal_data": {
        "roll": "445566",
        "registration": "998877665544",
        "student_name": "Roksana Akter",
        "father_name": "Mahbubur Rahman",
        "mother_name": "Amena Begum",
        "date_of_birth": "2004-12-30",
        "gender": "female",
        "session": "2022-2023",
        "name_of_industry": "Khulna Engineering College",
        "department": "Electrical Technology"
      },
      "subject_info": {}
    },
    {
      "id": 49,
      "personal_data": {
        "roll": "778899",
        "registration": "223344556677",
        "student_name": "Shanto Islam",
        "father_name": "Alomgir Hossain",
        "mother_name": "Marufa Akter",
        "date_of_birth": "2002-11-14",
        "gender": "male",
        "session": "2020-2021",
        "name_of_industry": "Chattogram Engineering College",
        "department": "Power Technology"
      },
      "subject_info": {}
    },
    {
      "id": 50,
      "personal_data": {
        "roll": "001122",
        "registration": "889900112233",
        "student_name": "Nishat Akter",
        "father_name": "Shahjahan Ali",
        "mother_name": "Morzina Khatun",
        "date_of_birth": "2005-03-09",
        "gender": "female",
        "session": "2024-2025",
        "name_of_industry": "Dhaka Mohila Polytechnic Institute",
        "department": "Finance"
      },
      "subject_info": {}
    }
  ]
}